podcast_chapter_tools/__init__.py
podcast_chapter_tools/entities.py
podcast_chapter_tools/extractors.py
podcast_chapter_tools/py.typed
podcast_chapter_tools-0.1.0.dist-info/LICENSE.txt
podcast_chapter_tools-0.1.0.dist-info/METADATA
podcast_chapter_tools-0.1.0.dist-info/WHEEL
podcast_chapter_tools-0.1.0.dist-info/top_level.txt
podcast_chapter_tools-0.1.0.dist-info/RECORD
