Metadata-Version: 2.1
Name: podcast-chapter-tools
Version: 0.1.0
Summary: Extract and transform podcast chapter information between PodCastIndex chapters, Podlove simple chapters, and description embeds.
Author-email: Harold Martin <Harold.Martin@gmail.com>
License: Apache License
Project-URL: Homepage, https://github.com/hbmartin/podcast-chapter-tools
Keywords: podcast,chapters,pci,psc,convert
Classifier: Development Status :: 4 - Beta
Classifier: Environment :: Console
Classifier: Framework :: Datasette
Classifier: Intended Audience :: End Users/Desktop
Classifier: Intended Audience :: Science/Research
Classifier: License :: OSI Approved :: Apache Software License
Classifier: Programming Language :: Python :: 3.11
Classifier: Programming Language :: Python :: 3.12
Classifier: Typing :: Typed
Requires-Python: >=3.11
License-File: LICENSE.txt
Requires-Dist: podcast-transcript-convert
Provides-Extra: lint
Requires-Dist: black ; extra == 'lint'
Requires-Dist: ruff ; extra == 'lint'
Requires-Dist: pyroma ; extra == 'lint'
Requires-Dist: pytype ; extra == 'lint'
